quantperf/__init__.py
quantperf-1.0.5.dist-info/METADATA
quantperf-1.0.5.dist-info/WHEEL
quantperf-1.0.5.dist-info/top_level.txt
quantperf-1.0.5.dist-info/RECORD
