Metadata-Version: 2.1
Name: quantperf
Version: 1.0.5
Summary: QuantPerf
Requires-Dist: pandas
